scalding/__init__.py
scalding-0.0.0.dist-info/LICENSE
scalding-0.0.0.dist-info/METADATA
scalding-0.0.0.dist-info/WHEEL
scalding-0.0.0.dist-info/top_level.txt
scalding-0.0.0.dist-info/RECORD
